imuthes/crypt/.git
imuthes/crypt/README.md
imuthes/crypt/__init__.py
imuthes/crypt/cli.py
imuthes/crypt/crypt.py
imuthes/crypt/linux.py
imuthes/crypt/win32.py
imuthes_crypt-0.1.0.dist-info/METADATA
imuthes_crypt-0.1.0.dist-info/WHEEL
imuthes_crypt-0.1.0.dist-info/RECORD
